LICENCE
MANIFEST.in
README.rst
dev-requirements.txt
requirements.txt
setup.py
inxpect/__init__.py
inxpect/inspect.py
inxpect.egg-info/PKG-INFO
inxpect.egg-info/SOURCES.txt
inxpect.egg-info/dependency_links.txt
inxpect.egg-info/requires.txt
inxpect.egg-info/top_level.txt
inxpect.egg-info/zip-safe
inxpect/expect/__init__.py
inxpect/expect/chain.py
inxpect/expect/dict.py
inxpect/expect/factory.py
inxpect/expect/getters.py
inxpect/expect/list.py
inxpect/expect/method.py
inxpect/expect/operator.py
inxpect/expect/pickle23.py
inxpect/expect/property.py
inxpect/expect/should.py
inxpect/tests/__init__.py
inxpect/tests/testChain.py
inxpect/tests/testDict.py
inxpect/tests/testDocExamples.py
inxpect/tests/testGetters.py
inxpect/tests/testInspect.py
inxpect/tests/testList.py
inxpect/tests/testProperty.py
inxpect/tests/testShould.py