Metadata-Version: 1.1
Name: inxpect
Version: 0.4.1
Summary: Intuitive inspect and expect
Home-page: http://www.python.org/pypi/inxpect
Author: Grégory Salvan
Author-email: apieum@gmail.com
License: LGPL
Platform: UNKNOWN
Classifier: Programming Language :: Python
Classifier: Programming Language :: Python :: 3
Classifier: Development Status :: 4 - Beta
Classifier: Environment :: Other Environment
Classifier: Intended Audience :: Developers
Classifier: License :: OSI Approved :: GNU Library or Lesser General Public License (LGPL)
Classifier: Operating System :: OS Independent
Classifier: Topic :: Software Development :: Libraries :: Python Modules
